.editorconfig
.gitignore
.gitlab-ci.yml
README.rst
diagram_layers.jpg
plugin_changelog.txt
plugin_version.txt
publish.settings.sh
publish.sh
pyproject.toml
test_hash.py
tsconfig.json
.idea/modules.xml
.idea/peek-plugin-diagram.iml
.idea/inspectionProfiles/Project_Default.xml
.idea/inspectionProfiles/profiles_settings.xml
peek_plugin_diagram/__init__.py
peek_plugin_diagram/plugin_package.json
peek_plugin_diagram.egg-info/PKG-INFO
peek_plugin_diagram.egg-info/SOURCES.txt
peek_plugin_diagram.egg-info/dependency_links.txt
peek_plugin_diagram.egg-info/requires.txt
peek_plugin_diagram.egg-info/top_level.txt
peek_plugin_diagram/_private/GridKeyIndexTest.py
peek_plugin_diagram/_private/PluginNames.py
peek_plugin_diagram/_private/__init__.py
peek_plugin_diagram/_private/alembic.ini
peek_plugin_diagram/_private/lookup_type_maps.py
peek_plugin_diagram/_private/admin-app/diagram.module.web.ts
peek_plugin_diagram/_private/admin-app/components/config-editor-edit-canvas/config-edit-canvas.component.html
peek_plugin_diagram/_private/admin-app/components/config-editor-edit-canvas/config-edit-canvas.component.scss
peek_plugin_diagram/_private/admin-app/components/config-editor-edit-canvas/config-edit-canvas.component.ts
peek_plugin_diagram/_private/admin-app/components/config-editor-edit-lookup-color/config-edit-lookup-color.component.html
peek_plugin_diagram/_private/admin-app/components/config-editor-edit-lookup-color/config-edit-lookup-color.component.scss
peek_plugin_diagram/_private/admin-app/components/config-editor-edit-lookup-color/config-edit-lookup-color.component.ts
peek_plugin_diagram/_private/admin-app/components/config-editor-edit-lookup-color-modal/config-editor-edit-lookup-color-modal.component.ts
peek_plugin_diagram/_private/admin-app/components/config-editor-edit-lookup-layer/config-edit-lookup-layer.component.html
peek_plugin_diagram/_private/admin-app/components/config-editor-edit-lookup-layer/config-edit-lookup-layer.component.scss
peek_plugin_diagram/_private/admin-app/components/config-editor-edit-lookup-layer/config-edit-lookup-layer.component.ts
