Metadata-Version: 2.4
Name: peek-plugin-diagram
Version: 5.1.4
Summary: Peek Plugin Diagram - generic diagram for mobile and desktop browser
Author-email: Synerty <contact@synerty.com>
Project-URL: Homepage, https://github.com/Synerty/peek-plugin-diagram
Keywords: Peek,Python,Platform,synerty
Requires-Dist: peek-plugin-base==5.1.4
Requires-Dist: Numpy
Requires-Dist: tinycss2>=1.2.1
Requires-Dist: colormath>=3.0.0
